noofa/__init__.py
noofa/exceptions.py
noofa/utils.py
noofa/builders/__init__.py
noofa/builders/builders.py
noofa/builders/caching.py
noofa/builders/enc.py
noofa/builders/exceptions.py
noofa/components/__init__.py
noofa/components/base.py
noofa/components/components.py
noofa/components/dataschema.py
noofa/components/exceptions.py
noofa/components/figures.py
noofa/components/mixins.py
noofa/components/pivot_chart.py
noofa/components/tables.py
noofa/components/utils.py
noofa/core/__init__.py
noofa/core/dataframes/__init__.py
noofa/core/dataframes/filters.py
noofa/core/dataframes/panda_builder.py
noofa/core/dataframes/utils.py
noofa/core/func/__init__.py
noofa/core/func/_functions.py
noofa/core/func/base.py
noofa/core/func/conn.py
noofa/core/func/context.py
noofa/core/func/datastruct.py
noofa/core/func/date.py
noofa/core/func/df.py
noofa/core/func/errors.py
noofa/core/func/interpreter.py
noofa/core/func/logic.py
noofa/core/func/numbers.py
noofa/core/func/operators.py
noofa/core/func/parser.py
noofa/core/func/sql.py
noofa/core/func/statistics.py
noofa/core/func/strings.py
noofa/core/func/typeconv.py
noofa/core/func/values.py
noofa/core/sources/__init__.py
noofa/core/sources/conn.py
noofa/core/sources/exceptions.py
noofa/core/sources/file_sources.py
noofa/core/sources/query.py
noofa/core/sources/statements.py
noofa/core/sources/utils.py
noofa/examples/__init__.py
noofa/examples/examples.py
noofa/pdf/__init__.py
noofa/pdf/pdf_builder.py
noofa/tests/__init__.py
noofa/tests/base.py
noofa/tests/test.py
noofa/tests/builders/__init__.py
noofa/tests/builders/builder.py
noofa/tests/components/__init__.py
noofa/tests/components/components.py
noofa/tests/components/dataschema.py
noofa/tests/df/__init__.py
noofa/tests/df/panda_builder.py
noofa/tests/df/panda_filters.py
noofa/tests/func/__init__.py
noofa/tests/func/context.py
noofa/tests/func/datastruct.py
noofa/tests/func/date.py
noofa/tests/func/df.py
noofa/tests/func/expr.py
noofa/tests/func/interpreter.py
noofa-0.1.1.dist-info/LICENSE
noofa-0.1.1.dist-info/METADATA
noofa-0.1.1.dist-info/WHEEL
noofa-0.1.1.dist-info/top_level.txt
noofa-0.1.1.dist-info/RECORD
