Metadata-Version: 2.1
Name: noofa
Version: 0.1.1
Summary: Reports backend package
Author-email: Maxim Peshkin <existentiary@gmail.com>
Project-URL: Homepage, https://github.com/milkywayisdead/noofa
Project-URL: Bug Tracker, https://github.com/milkywayisdead/noofa/issues
Classifier: Programming Language :: Python :: 3
Classifier: License :: OSI Approved :: MIT License
Classifier: Operating System :: OS Independent
Requires-Python: <4,>=3.8
License-File: LICENSE
Requires-Dist: kaleido
Requires-Dist: mysql-connector-python
Requires-Dist: pandas
Requires-Dist: plotly
Requires-Dist: psycopg2-binary
Requires-Dist: pyodbc
Requires-Dist: reportlab
Requires-Dist: redis
Requires-Dist: requests
